{
	"name": "demo",
	"children": [
		{
			"name": "First Parent",
			"children": [
				{
					"name": "First Child",
					"children": [
						{
							"name": "First GrandChild",
							"size": 60
						},
						{
							"name": "Second GrandChild",
							"size": 30
						},
						{
							"name": "Third GrandChild",
							"size": 70
						}
					]
				},
				{
					"name": "Second Child",
					"children": [
						{
							"name": "First GrandChild",
							"size": 60
						},
						{
							"name": "Second GrandChild",
							"size": 50
						},
						{
							"name": "Third GrandChild",
							"size": 20
						},
						{
							"name": "Third GrandChild",
							"size": 40
						}
					]
				}
			]
		},
		{
			"name": "Second Parent",
			"children": [
				{
					"name": "First Child",
					"size": 100
				},
				{
					"name": "Second Child",
					"size": 100
				}
			]
		},
		{
			"name": "Third Parent",
			"children": [
				{
					"name": "First Child",
					"size": 120
				},
				{
					"name": "Second Child",
					"size": 80
				},
				{
					"name": "Third Child",
					"size": 50
				}
			]
		},
		{
			"name": "Fourth Parent",
			"children": [
				{
					"name": "First Child",
					"size": 60
				},
				{
					"name": "Second Child",
					"size": 30
				}
			]
		},
		{
			"name": "Fifth Parent",
			"children": [
				{
					"name": "First Child",
					"size": 60
				},
				{
					"name": "Second Child",
					"size": 30
				},
				{
					"name": "Third Child",
					"size": 50
				},
				{
					"name": "Fourth Child",
					"size": 80
				}
			]
		}
	]
}